{
    "pages": [
        {
            "name": "applicantsPage",
            "elements": [
                {
                    "type": "panel",
                    "name": "applicantsIntroPanel",
                    "elements": [
                        {
                            "type": "infotext",
                            "name": "applicantIntroExplanation",
                            "title": "This step is to identify who is applying to represent {deceasedName}.",
                            "titleLocation": "hidden"
                        }
                    ]
                },
                {
                    "type": "panel",
                    "name": "applicantPanel",
                    "elements": [
                        {
                            "type": "radiogroup",
                            "name": "applicantName",
                            "title": "Who is applying to represent  and manage {deceasedName}'s property, money and belongings?",
                            "description": "Here is a list of the people you have identified so far in this service.\n<br><br>\nIf you have already included yourself in previous steps, you will still need to identify if you are applying for a `Representation Grant` for {deceasedName}  in this step.",
                            "hasOther": true,
                            "choices": [
                                {
                                    "value": "relatedPerson",
                                    "text": "Jillian Patricia Taylor"
                                }
                            ],
                            "otherText": "Add a different applicant"
                        },
                        {
                            "type": "helptext",
                            "name": "applicantFAQ1",
                            "title": "Can more than 1 person apply to represent {deceasedName}?",
                            "titleLocation": "hidden",
                            "body": "Yes, normally, more than 1 person can apply together to represent {deceasedName}. \n<br><br>\nMultiple `personal representatives` can help share the workload but it may also require a lot of scheduling time together.\n<br><br>\nSome organizations may require all of {deceasedName}'s personal representatives to meet in-person and sign documents at the same time.\n<br><br>\n<b>However, if 2 or more people want to apply together, this service cannot help you at this time.</b> For now, this service has only been developed for a limited number of situations.\n<br><br>\n<b>Please check later to see if this service has been developed for your specific situation.</b> This service is continuously expanding to help more and more people.</b> \n<br><br>\nIn the mean time, the Government of British Columbia offers PDF forms that you may find helpful for your application. <a href=\"https://www2.gov.bc.ca/gov/content/justice/courthouse-services/documents-forms-records/court-forms/probate-forms\" target=\"_blank\">Click here to go to the forms.</a> (This link opens in a new tab)"
                        }
                    ]
                },
                {
                    "type": "panel",
                    "name": "applicantInfoPanel",   
                    "elements": [      
                        {
                         "type": "text",
                         "name": "applicantOccupation",
                         "title": "What is {applicantName}'s job or profession?",
                         "description": "For example: Nurse, Homemaker, Carpenter, Accountant, etc.",
                         "isRequired": true
                        },
                        {
                         "type": "address",
                         "name": "applicantOrdinaryAddress",
                         "title": "Where does {applicantName} normally live?",
                         "isRequired": true
                        },
                        {
                         "type": "helptext",
                         "name": "applicantOrdinaryAddressFAQ1",
                         "title": "What if {applicantName} is homeless?",
                         "titleLocation": "hidden",
                         "body": "If {applicantName} was homeless,<ul><li>Write \"no fixed address\" for the street number and street name.</li><li>Write the City/Town, Province, and Country where they lived.</li><li>Write \"n/a\" for their Postal Code.</li></ul>"
                        },
                        {
                         "type": "yesno",
                         "name": "applicantOrdinaryAddressReceiveMail",
                         "title": "Does {applicantName} receive mail at this address?",
                         "isRequired": true
                        },
                        {
                         "type": "address",
                         "name": "applicantMailingAddress",
                         "visible": false,
                         "visibleIf": "{applicantOrdinaryAddressReceiveMail} = 'n'",
                         "title": "Where does {applicantName} receive mail?",
                         "isRequired": true
                        }    
                    ],
                    "visible": false,
                    "visibleIf": "{applicantName} notempty"
                },
                {
                    "type": "panel",
                    "name": "citationInfoPanel",
                    "elements": [
                        {
                            "type": "yesno",
                            "name": "applicantCited",
                            "title": "Did {applicantName} receive a `citation`?",
                            "isRequired": true
                        },
                        {
                            "type": "infotext",
                            "name": "applicantCitedReviewCheckRelationsExist",
                            "visible": false,
                            "visibleIf": "{applicantCited} = 'y' and ({relatedPeopleExist})",
                            "title": "In past steps, you have already identified the following people:\n{relatedPeopleInfo}\nBecause you are already letting these people know that you are applying for a Representation Grant, you do not need to identify them again even if they gave you a citation.",
                            "titleLocation": "hidden"
                        },
                        {
                            "type": "infotext",
                            "name": "applicantCitedReviewCheckRelationsDontExist",
                            "visible": false,
                            "visibleIf": "{applicantCited} = 'y' and !({relatedPeopleExist})",
                            "title": "In past steps, you have not yet identified anyone else who needs to know that you are applying for a `Representation Grant` for {deceasedName}.",
                            "titleLocation": "hidden"
                        },
                        {
                            "type": "yesno",
                            "name": "applicantCitorNewExists",
                            "visible": false,
                            "visibleIf": "{applicantCited} = 'y'",
                            "title": "Is there someone that is NOT in the above list who gave {applicantName} a citation?",
                            "description": "If someone in the above list gave {applicantName} a citation, you do NOT need to identify them again them because this service will already help you tell them you applying for a `Representation Grant` for {deceasedName}."
                        }
                    ],
                    "visible": false,
                    "visibleIf": "{applicantName} notempty"
                }
            ],
            "title": "The Applicant(s)"
        }
    ],
    "showQuestionNumbers": "off",
    "requiredText": ""
}